<bassin>
  <canvas width="1641" height="982" fish_size="127" bg="C:\Users\Admin\CLionProjects\gtk\resources\images\fond\background2.png" elapsed_time="69.201000" num_bancs="3"/>
  <poissons>
    <poisson id="13" nom="Eel" x="741.066531" y="628.820104" vx="2.833040" vy="49.919674" id_banc="3" est_leader="false" sante="100.000000"/>
    <poisson id="12" nom="Eel" x="687.960404" y="664.221775" vx="3.463585" vy="49.879892" id_banc="3" est_leader="false" sante="100.000000"/>
    <poisson id="11" nom="Eel" x="727.527029" y="672.157875" vx="2.966332" vy="49.911931" id_banc="3" est_leader="false" sante="100.000000"/>
    <poisson id="10" nom="Eel" x="696.919379" y="626.834569" vx="0.146212" vy="49.999786" id_banc="3" est_leader="false" sante="100.000000"/>
    <poisson id="9" nom="Eel" x="711.587419" y="714.357449" vx="-0.573180" vy="49.996715" id_banc="3" est_leader="true" sante="100.000000"/>
    <poisson id="8" nom="scate" x="797.125538" y="501.627956" vx="-39.810949" vy="-3.884366" id_banc="2" est_leader="false" sante="100.000000"/>
    <poisson id="7" nom="scate" x="816.462117" y="523.517296" vx="-39.933211" vy="-2.310551" id_banc="2" est_leader="false" sante="100.000000"/>
    <poisson id="6" nom="scate" x="802.160755" y="480.595551" vx="-39.674873" vy="-5.089641" id_banc="2" est_leader="false" sante="100.000000"/>
    <poisson id="5" nom="scate" x="758.979735" y="494.406692" vx="-39.772078" vy="-4.264011" id_banc="2" est_leader="true" sante="100.000000"/>
    <poisson id="4" nom="turtle" x="1141.061012" y="361.342873" vx="22.909688" vy="-10.007307" id_banc="1" est_leader="false" sante="100.000000"/>
    <poisson id="3" nom="turtle" x="1180.732157" y="339.298779" vx="23.028376" vy="-9.731078" id_banc="1" est_leader="false" sante="100.000000"/>
    <poisson id="2" nom="turtle" x="1183.726448" y="346.568291" vx="23.029082" vy="-9.729407" id_banc="1" est_leader="false" sante="100.000000"/>
    <poisson id="1" nom="turtle" x="1228.879148" y="323.212968" vx="23.172455" vy="-9.382820" id_banc="1" est_leader="true" sante="100.000000"/>
  </poissons>
</bassin>
